Workbook

Sheet Dashboard
A1: Investment Portfolio Dashboard
B4: Inputs | E4: Portfolio Overview
B5: Initial Investment (£) | C5: ='Portfolio Data'!G15 -> 17480 | E5: Largest Holding | F5: Visa
B6: Cash Available (£) | C6: 6800 | E6: Largest Sector | F6: Technology
E7: Average Return (%) | F7: =AVERAGE('Portfolio Data'!J4:J13) -> 0.14380248
E8: Number of Sectors | F8: 7
B9: Portfolio Summary
B10: Total Portfolio Value (£) | C10: ='Portfolio Data'!H15 -> 19882
B11: Total Profit/Loss (£) | C11: ='Portfolio Data'!I15 -> 2402 | E11: Key Highlights:
B12: Total Return (%) | C12: =C11/('Portfolio Data'!G15) -> 0.13741419 | E12: Portfolio Return: 13.74%
B13: Best Performing Stock | C13: NVIDIA | E13: Largest Sector: Technology
B14: Worst Performing Stock | C14: Unilever | E14: Best Performer: NVIDIA
B15: Number of Holdings | C15: =COUNTA('Portfolio Data'!B4:B13) -> 10

Sheet Portfolio Data
A1: Investment Portfolio Data
B3: Company | C3: Sector | D3: Shares Owned | E3: Purchase Price (£) | F3: Current Price (£) | G3: Total Cost (£) | H3: Current Value (£) | I3: Profit/Loss (£) | J3: Return (%)
B4: Apple | C4: Technology | D4: 10 | E4: 170 | F4: 195 | G4: =D4*E4 -> 1700 | H4: =D4*F4 -> 1950 | I4: =H4-G4 -> 250 | J4: =I4/G4 -> 0.14705882
B5: Microsoft | C5: Technology | D5: 8 | E5: 380 | F5: 420 | G5: =D5*E5 -> 3040 | H5: =D5*F5 -> 3360 | I5: =H5-G5 -> 320 | J5: =I5/G5 -> 0.10526316
B6: NVIDIA | C6: Technology | D6: 12 | E6: 110 | F6: 145 | G6: =D6*E6 -> 1320 | H6: =D6*F6 -> 1740 | I6: =H6-G6 -> 420 | J6: =I6/G6 -> 0.31818182
B7: JPMorgan Chase | C7: Financials | D7: 15 | E7: 170 | F7: 185 | G7: =D7*E7 -> 2550 | H7: =D7*F7 -> 2775 | I7: =H7-G7 -> 225 | J7: =I7/G7 -> 0.088235294
B8: Visa | C8: Financials | D8: 14 | E8: 250 | F8: 285 | G8: =D8*E8 -> 3500 | H8: =D8*F8 -> 3990 | I8: =H8-G8 -> 490 | J8: =I8/G8 -> 0.14
B9: Shell | C9: Energy | D9: 20 | E9: 28 | F9: 31 | G9: =D9*E9 -> 560 | H9: =D9*F9 -> 620 | I9: =H9-G9 -> 60 | J9: =I9/G9 -> 0.10714286
B10: Coca-Cola | C10: Consumer Staples | D10: 18 | E10: 60 | F10: 68 | G10: =D10*E10 -> 1080 | H10: =D10*F10 -> 1224 | I10: =H10-G10 -> 144 | J10: =I10/G10 -> 0.13333333
B11: Unilever | C11: Consumer Goods | D11: 25 | E11: 40 | F11: 43 | G11: =D11*E11 -> 1000 | H11: =D11*F11 -> 1075 | I11: =H11-G11 -> 75 | J11: =I11/G11 -> 0.075
B12: AstraZeneca | C12: Healthcare | D12: 16 | E12: 105 | F12: 118 | G12: =D12*E12 -> 1680 | H12: =D12*F12 -> 1888 | I12: =H12-G12 -> 208 | J12: =I12/G12 -> 0.12380952
B13: Amazon | C13: Consumer Discretionary | D13: 6 | E13: 175 | F13: 210 | G13: =D13*E13 -> 1050 | H13: =D13*F13 -> 1260 | I13: =H13-G13 -> 210 | J13: =I13/G13 -> 0.2
B15: Totals | G15: =SUM(G4:G13) -> 17480 | H15: =SUM(H4:H13) -> 19882 | I15: =SUM(I4:I13) -> 2402

Sheet Analysis
A1: Investment Portfolio Analysis
B3: 1. Compnay Performance Analysis
B5: Company | C5: Profit/Loss (£)
B6: Apple | C6: 250
B7: Microsoft | C7: 320
B8: NVIDIA | C8: 420
B9: JPMorgan Chase | C9: 225
B10: Visa | C10: 490
B11: Shell | C11: 60
B12: Coca-Cola | C12: 144
B13: Unilever | C13: 75
B14: AstraZeneca | C14: 208
B15: Amazon | C15: 210
B20: 2. Portfolio Allocation by Sector
B22: Sector | C22: Total Market Value (£)
B23: Technology | C23: ='Portfolio Data'!H4+'Portfolio Data'!H5+'Portfolio Data'!H6 -> 7050
B24: Financials | C24: ='Portfolio Data'!H7+'Portfolio Data'!H8 -> 6765
B25: Energy | C25: ='Portfolio Data'!H9 -> 620
B26: Consumer Staples | C26: ='Portfolio Data'!H10 -> 1224
B27: Consumer Goods | C27: ='Portfolio Data'!H11 -> 1075
B28: Healthcare | C28: ='Portfolio Data'!H12 -> 1888
B29: Consumer Discretionary | C29: ='Portfolio Data'!H13 -> 1260
B37: 3. Portfolio Value by Company
B39: Company | C39: Current Value (£)
B40: Apple | C40: ='Portfolio Data'!H4 -> 1950
B41: Microsoft | C41: ='Portfolio Data'!H5 -> 3360
B42: NVIDIA | C42: ='Portfolio Data'!H6 -> 1740
B43: JPMorgan Chase | C43: ='Portfolio Data'!H7 -> 2775
B44: Visa | C44: ='Portfolio Data'!H8 -> 3990
B45: Shell | C45: ='Portfolio Data'!H9 -> 620
B46: Coca-Cola | C46: ='Portfolio Data'!H10 -> 1224
B47: Unilever | C47: ='Portfolio Data'!H11 -> 1075
B48: AstraZeneca | C48: ='Portfolio Data'!H12 -> 1888
B49: Amazon | C49: ='Portfolio Data'!H13 -> 1260
B55: Key Findings:
B56: Visa is the largest individual holding, with a current value of £3,990
B57: Technology is the largest sector, representing the biggest share of the portfolio
B58: The portfolio has generated a total return of 13.74%, equivalent to a profit of £2,402
B59: The portfolio is diversified across 7 different sectors, which reduces concentration risk
